psyke/__init__.py
psyke/hypercubepredictor.py
psyke/clustering/__init__.py
psyke/clustering/utils.py
psyke/clustering/cream/__init__.py
psyke/clustering/exact/__init__.py
psyke/extraction/__init__.py
psyke/extraction/cart/CartPredictor.py
psyke/extraction/cart/FairTree.py
psyke/extraction/cart/FairTreePredictor.py
psyke/extraction/cart/__init__.py
psyke/extraction/hypercubic/__init__.py
psyke/extraction/hypercubic/hypercube.py
psyke/extraction/hypercubic/strategy.py
psyke/extraction/hypercubic/utils.py
psyke/extraction/hypercubic/cosmik/__init__.py
psyke/extraction/hypercubic/creepy/__init__.py
psyke/extraction/hypercubic/divine/__init__.py
psyke/extraction/hypercubic/ginger/__init__.py
psyke/extraction/hypercubic/gridex/__init__.py
psyke/extraction/hypercubic/gridrex/__init__.py
psyke/extraction/hypercubic/hex/__init__.py
psyke/extraction/hypercubic/iter/__init__.py
psyke/extraction/real/__init__.py
psyke/extraction/real/utils.py
psyke/extraction/trepan/__init__.py
psyke/extraction/trepan/utils.py
psyke/genetic/__init__.py
psyke/genetic/fgin/__init__.py
psyke/genetic/gin/__init__.py
psyke/schema/__init__.py
psyke/tuning/__init__.py
psyke/tuning/crash/__init__.py
psyke/tuning/orchid/__init__.py
psyke/tuning/pedro/__init__.py
psyke/utils/__init__.py
psyke/utils/dataframe.py
psyke/utils/logic.py
psyke/utils/metrics.py
psyke/utils/plot.py
psyke/utils/sorted.py
psyke-0.10.4.dist-info/licenses/LICENSE
psyke-0.10.4.dist-info/METADATA
psyke-0.10.4.dist-info/WHEEL
psyke-0.10.4.dist-info/top_level.txt
psyke-0.10.4.dist-info/RECORD
