Metadata-Version: 2.4
Name: psyke
Version: 0.10.4
Summary: Python-based implementation of PSyKE, i.e. a Platform for Symbolic Knowledge Extraction
Home-page: https://github.com/psykei/psyke-python
Author: Matteo Magnini
Author-email: matteo.magnini@unibo.it
License: Apache 2.0 License
Project-URL: Bug Reports, https://github.com/psykei/psyke-python/issues
Project-URL: Source, https://github.com/psykei/psyke-python
Keywords: knowledge extraction,symbolic ai,ske,extractor,rules,prolog
Platform: Independant
Classifier: Development Status :: 3 - Alpha
Classifier: Intended Audience :: Developers
Classifier: Topic :: Software Development :: Libraries
Classifier: Topic :: Scientific/Engineering :: Artificial Intelligence
Classifier: License :: OSI Approved :: Apache Software License
Classifier: Programming Language :: Python :: 3
Classifier: Programming Language :: Python :: 3.9
Classifier: Programming Language :: Python :: 3 :: Only
Classifier: Programming Language :: Prolog
Requires-Python: >=3.9.0, <3.10
License-File: LICENSE
Requires-Dist: numpy~=1.26.0
Requires-Dist: pandas~=2.3.0
Requires-Dist: scikit-learn~=1.6.0
Requires-Dist: 2ppy~=0.4.0
Requires-Dist: kneed~=0.8.1
Requires-Dist: sympy~=1.11
Dynamic: author
Dynamic: author-email
Dynamic: classifier
Dynamic: description
Dynamic: description-content-type
Dynamic: home-page
Dynamic: keywords
Dynamic: license
Dynamic: license-file
Dynamic: platform
Dynamic: project-url
Dynamic: requires-dist
Dynamic: requires-python
Dynamic: summary
